README.md
setup.py
qpbane/__init__.py
qpbane/bruteforcer.py
qpbane/ddos.py
qpbane/extrafun.py
qpbane/hasher.py
qpbane/infos.py
qpbane/iot.py
qpbane/pager.py
qpbane/payloads.py
qpbane/proxer.py
qpbane/vulns.py
qpbane/wp.py
qpbane.egg-info/PKG-INFO
qpbane.egg-info/SOURCES.txt
qpbane.egg-info/dependency_links.txt
qpbane.egg-info/requires.txt
qpbane.egg-info/top_level.txt